landuse_intensity/__init__.py
landuse_intensity/core.py
landuse_intensity/graph_visualization.py
landuse_intensity/image_processing.py
landuse_intensity/map_visualization.py
landuse_intensity/raster.py
landuse_intensity/utils.py
landuse_intensity/visualization.py
landuse_intensity_analysis-2.0.4.dist-info/licenses/LICENSE
landuse_intensity_analysis-2.0.4.dist-info/METADATA
landuse_intensity_analysis-2.0.4.dist-info/WHEEL
landuse_intensity_analysis-2.0.4.dist-info/top_level.txt
landuse_intensity_analysis-2.0.4.dist-info/RECORD
