Metadata-Version: 2.4
Name: landuse-intensity-analysis
Version: 2.0.4
Summary: Comprehensive Python library for scientifically rigorous land use change analysis using the Pontius-Aldwaik intensity analysis methodology. Complete API with contingency tables, intensity analysis, and rich visualizations.
Author-email: LandUse Intensity Analysis Contributors <contact@landuse-intensity.org>
Maintainer-email: LandUse Intensity Analysis Contributors <contact@landuse-intensity.org>
License-Expression: MIT
Project-URL: Homepage, https://github.com/ils15/LandUse-Intensity-Analysis
Project-URL: Documentation, https://landuse-intensity-analysis.readthedocs.io
Project-URL: Repository, https://github.com/ils15/LandUse-Intensity-Analysis
Project-URL: Bug Tracker, https://github.com/ils15/LandUse-Intensity-Analysis/issues
Project-URL: Changelog, https://github.com/ils15/LandUse-Intensity-Analysis/blob/main/CHANGELOG.md
Keywords: land-use,intensity-analysis,pontius,aldwaik,remote-sensing,gis,land-change,spatial-analysis,environmental-science
Classifier: Development Status :: 5 - Production/Stable
Classifier: Intended Audience :: Science/Research
Classifier: Operating System :: OS Independent
Classifier: Programming Language :: Python :: 3
Classifier: Programming Language :: Python :: 3.8
Classifier: Programming Language :: Python :: 3.9
Classifier: Programming Language :: Python :: 3.10
Classifier: Programming Language :: Python :: 3.11
Classifier: Programming Language :: Python :: 3.12
Classifier: Topic :: Scientific/Engineering :: GIS
Classifier: Topic :: Scientific/Engineering :: Information Analysis
Classifier: Topic :: Scientific/Engineering :: Visualization
Requires-Python: >=3.8
License-File: LICENSE
Requires-Dist: numpy>=1.20.0
Requires-Dist: pandas>=1.3.0
Requires-Dist: matplotlib>=3.4.0
Requires-Dist: seaborn>=0.11.0
Requires-Dist: xarray>=0.16.0
Requires-Dist: rasterio>=1.2.0
Requires-Dist: rioxarray>=0.8.0
Requires-Dist: plotly>=5.0.0
Requires-Dist: holoviews>=1.14.0
Requires-Dist: scipy>=1.7.0
Requires-Dist: pydantic>=2.0.0
Requires-Dist: pyyaml>=6.0
Requires-Dist: psutil>=5.8.0
Requires-Dist: tqdm>=4.62.0
Provides-Extra: spatial
Requires-Dist: geopandas>=0.10.0; extra == "spatial"
Requires-Dist: shapely>=1.8.0; extra == "spatial"
Requires-Dist: contextily>=1.2.0; extra == "spatial"
Requires-Dist: folium>=0.12.0; extra == "spatial"
Requires-Dist: mapclassify>=2.4.0; extra == "spatial"
Provides-Extra: parallel
Requires-Dist: dask[complete]>=2022.0.0; extra == "parallel"
Requires-Dist: ray[default]>=2.0.0; extra == "parallel"
Requires-Dist: numba>=0.56.0; extra == "parallel"
Provides-Extra: compression
Requires-Dist: lz4>=4.0.0; extra == "compression"
Provides-Extra: dev
Requires-Dist: pytest>=6.0; extra == "dev"
Requires-Dist: pytest-cov>=2.12; extra == "dev"
Requires-Dist: black>=21.0; extra == "dev"
Requires-Dist: flake8>=3.9; extra == "dev"
Requires-Dist: mypy>=0.910; extra == "dev"
Requires-Dist: pre-commit>=2.15; extra == "dev"
Provides-Extra: docs
Requires-Dist: sphinx>=4.0; extra == "docs"
Requires-Dist: sphinx-rtd-theme>=1.0; extra == "docs"
Requires-Dist: myst-parser>=0.15; extra == "docs"
Dynamic: license-file
